lowrankdensity/__init__.py
lowrankdensity/datasets/__init__.py
lowrankdensity/datasets/generate_samples.py
lowrankdensity/models/__init__.py
lowrankdensity/models/continuous.py
lowrankdensity/models/discrete.py
lowrankdensity_summer_school_2025-0.0.3.dist-info/licenses/LICENSE
lowrankdensity_summer_school_2025-0.0.3.dist-info/METADATA
lowrankdensity_summer_school_2025-0.0.3.dist-info/WHEEL
lowrankdensity_summer_school_2025-0.0.3.dist-info/top_level.txt
lowrankdensity_summer_school_2025-0.0.3.dist-info/RECORD
